csl_reference/__init__.py
csl_reference/_reference.py
csl_reference/_version.py
csl_reference-0.1.1.dist-info/METADATA
csl_reference-0.1.1.dist-info/WHEEL
csl_reference-0.1.1.dist-info/licenses/LICENCE
csl_reference-0.1.1.dist-info/RECORD
